{
  "version": 2,
  "extractor": "pdffigures2",
  "figures": [
    {
      "url": "assets/figures/arxiv/2604.24023v1/fig-001.webp",
      "caption": "Figure 4: Overview of ServImageModel: (a) Two-stage ServImageModel architecture; (b) Accuracy comparison of base models and our variants. (c) Radar chart of Accuracy Comparison Result.",
      "page": 6,
      "index": 1,
      "width": 944,
      "height": 451
    },
    {
      "url": "assets/figures/arxiv/2604.24023v1/fig-002.webp",
      "caption": "Table 9: Model performance on ServImage under the standard settlement scenario, estimated using ServImageModel-predicted payment probabilities. Revenue, Rev ($k), is the total contract value estimated from predicted accept/reject outcomes, and Share is its fraction of the overall contract value ($295k), while category shares are computed within each category. Task Acceptance and Deliverable Acceptance are the predicted proportions of tasks and deliverables approved under ServImageModel. (See Table 2 for results based on human",
      "page": 25,
      "index": 2,
      "width": 889,
      "height": 350
    },
    {
      "url": "assets/figures/arxiv/2604.24023v1/fig-003.webp",
      "caption": "Table 13: Representative failure examples grouped by dominant failure dimension. Dominant Score denotes the score of the lowest-scoring dimension for the corresponding sample, which determines the failure label used in Table 12. Whenmultiple dimensions tie for the minimum score, the example is assigned according to the predefined tie-breaking rule used in our analysis pipeline.",
      "page": 26,
      "index": 3,
      "width": 950,
      "height": 595
    },
    {
      "url": "assets/figures/arxiv/2604.24023v1/fig-004.webp",
      "caption": "Figure 7: Task case 2.",
      "page": 15,
      "index": 4,
      "width": 929,
      "height": 881
    },
    {
      "url": "assets/figures/arxiv/2604.24023v1/fig-005.webp",
      "caption": "Figure 12: VEQ-Aesthetic Quality AND Text Quality Evaluation prompt.",
      "page": 21,
      "index": 5,
      "width": 929,
      "height": 1362
    },
    {
      "url": "assets/figures/arxiv/2604.24023v1/fig-006.webp",
      "caption": "Figure 1: Overview of the ServImage benchmark and evaluation framework. (a) We collect 1,070 paid design tasks from online crowdsourcing platforms and group them into Portrait, Product, and Digital categories. (b) Through the dataset pipeline with rule extraction/point mining, we obtain BRF, VEQ, and CNS scores to form ServImageScore. (c) Sixteen image generation and editing models produce about 33k candidate images. (d) Optionally, built on these scores, ServImageModel predicts human payment decisions. (e) We present representative tasks and model outputs as ServImage case studies. (f) Under the standard settlement scenario, we evaluate each model independently on the full task set and compare their commercial capability using the economic metric of total revenue.",
      "page": 2,
      "index": 6,
      "width": 941,
      "height": 465
    },
    {
      "url": "assets/figures/arxiv/2604.24023v1/fig-007.webp",
      "caption": "Table 3: Crowdsourcing competition earnings with winner-takes-all acceptance. We report total value earned Rev which means Revenue, and Rank. Color:",
      "page": 7,
      "index": 7,
      "width": 436,
      "height": 436
    },
    {
      "url": "assets/figures/arxiv/2604.24023v1/fig-008.webp",
      "caption": "Table 2: Model performance on ServImage under the standard settlement scenario. Revenue, Rev ($k), is the total contract value earned by a model, and Share is its fraction of the overall contract value ($295k), while category shares are computed within each category. Task Acceptance and Deliverable Acceptance are the proportions of tasks and deliverables approved according to human payment decisions (yt,i). The last six columns report revenue",
      "page": 7,
      "index": 8,
      "width": 862,
      "height": 358
    },
    {
      "url": "assets/figures/arxiv/2604.24023v1/fig-009.webp",
      "caption": "Figure 13: CNS-Edit Evaluation prompt.",
      "page": 22,
      "index": 9,
      "width": 929,
      "height": 696
    },
    {
      "url": "assets/figures/arxiv/2604.24023v1/fig-010.webp",
      "caption": "Figure 9: Prompt for evaluation points extraction.",
      "page": 18,
      "index": 10,
      "width": 929,
      "height": 1237
    },
    {
      "url": "assets/figures/arxiv/2604.24023v1/fig-011.webp",
      "caption": "Figure 14: CNS-Set Evaluation prompt.",
      "page": 23,
      "index": 11,
      "width": 891,
      "height": 924
    },
    {
      "url": "assets/figures/arxiv/2604.24023v1/fig-012.webp",
      "caption": "Table 7: Cost reduction under the standard settlement",
      "page": 13,
      "index": 12,
      "width": 458,
      "height": 385
    },
    {
      "url": "assets/figures/arxiv/2604.24023v1/fig-013.webp",
      "caption": "Table 6: Per-call API prices (USD) assumed for each model in our experiments.",
      "page": 13,
      "index": 13,
      "width": 431,
      "height": 434
    },
    {
      "url": "assets/figures/arxiv/2604.24023v1/fig-014.webp",
      "caption": "Figure 5: Metric comparison on the test set. Bars show AUC, Spearman, and PR-AUC for seven metrics and ServImageScore, higher is better.",
      "page": 8,
      "index": 14,
      "width": 457,
      "height": 268
    },
    {
      "url": "assets/figures/arxiv/2604.24023v1/fig-015.webp",
      "caption": "Table 8: Model performance on ServImage by category under the standard settlement scenario. Revenue is the total contract value earned by a model in each category. Task Acceptance and Deliverable Acceptance are the within-category proportions of tasks and deliverables approved according to human payment decisions (yt,i). All monetary values are reported in thousand USD.",
      "page": 17,
      "index": 15,
      "width": 923,
      "height": 1310
    },
    {
      "url": "assets/figures/arxiv/2604.24023v1/fig-016.webp",
      "caption": "Figure 11: VEQ-Tech Evaluation prompt.",
      "page": 20,
      "index": 16,
      "width": 929,
      "height": 1045
    },
    {
      "url": "assets/figures/arxiv/2604.24023v1/fig-017.webp",
      "caption": "Figure 8: Task case 3.",
      "page": 16,
      "index": 17,
      "width": 929,
      "height": 1237
    }
  ]
}