{
  "version": 2,
  "extractor": "papercropper",
  "figures": [
    {
      "url": "assets/figures/arxiv/2605.22060v1/fig-001.webp",
      "caption": "",
      "page": 0,
      "index": 1,
      "width": 872,
      "height": 455,
      "label": "Figure"
    },
    {
      "url": "assets/figures/arxiv/2605.22060v1/fig-002.webp",
      "caption": "",
      "page": 0,
      "index": 2,
      "width": 1385,
      "height": 886,
      "label": "Figure"
    },
    {
      "url": "assets/figures/arxiv/2605.22060v1/fig-003.webp",
      "caption": "",
      "page": 0,
      "index": 3,
      "width": 701,
      "height": 521,
      "label": "Figure"
    },
    {
      "url": "assets/figures/arxiv/2605.22060v1/fig-004.webp",
      "caption": "",
      "page": 0,
      "index": 4,
      "width": 833,
      "height": 533,
      "label": "Figure"
    },
    {
      "url": "assets/figures/arxiv/2605.22060v1/fig-005.webp",
      "caption": "",
      "page": 0,
      "index": 5,
      "width": 830,
      "height": 622,
      "label": "Figure"
    },
    {
      "url": "assets/figures/arxiv/2605.22060v1/fig-006.webp",
      "caption": "",
      "page": 0,
      "index": 6,
      "width": 864,
      "height": 363,
      "label": "Figure"
    },
    {
      "url": "assets/figures/arxiv/2605.22060v1/fig-007.webp",
      "caption": "",
      "page": 0,
      "index": 7,
      "width": 862,
      "height": 413,
      "label": "Figure"
    }
  ]
}