{
  "version": 2,
  "extractor": "pdffigures2",
  "figures": [
    {
      "url": "assets/figures/arxiv/2605.05689v1/fig-001.webp",
      "caption": "Table 4: GCCM hyperparameters for seven datasets from [19] and [20].",
      "page": 18,
      "index": 1,
      "width": 822,
      "height": 230
    },
    {
      "url": "assets/figures/arxiv/2605.05689v1/fig-002.webp",
      "caption": "Table 5: Test performance on five benchmarks from [19]. Shown is the mean ± std of five runs with different seeds.",
      "page": 18,
      "index": 2,
      "width": 818,
      "height": 321
    },
    {
      "url": "assets/figures/arxiv/2605.05689v1/fig-003.webp",
      "caption": "Table 1: Test performance on benchmarks from [19, 20]. Results for baselines (except GPS, GRIT, GPS-LGD, and GPS-PCL) are taken from [3].",
      "page": 8,
      "index": 3,
      "width": 822,
      "height": 262
    },
    {
      "url": "assets/figures/arxiv/2605.05689v1/fig-004.webp",
      "caption": "Figure 1: Illustration of Graph Contrastive Consistency Models (GCCM). Compared with vanilla consistency training for graph prediction, which uses db to enforce the boundary condition and ds to enforce the self-consistency constraint, GCCM introduces contrastive consistency via dc on representations from two independently noisy labels, and further mitigates the shortcut solution via feature perturbation that breaks identical conditioning across consistency passes.",
      "page": 4,
      "index": 4,
      "width": 818,
      "height": 214
    },
    {
      "url": "assets/figures/arxiv/2605.05689v1/fig-005.webp",
      "caption": "Table 6: Efficiency comparison of GCCM against baselines across five benchmarks from [19].",
      "page": 19,
      "index": 5,
      "width": 818,
      "height": 321
    },
    {
      "url": "assets/figures/arxiv/2605.05689v1/fig-006.webp",
      "caption": "Figure 2: Heatmap visualizations of the contribution terms of WyYt and Wttemb(t) to H (0) t on",
      "page": 9,
      "index": 6,
      "width": 446,
      "height": 280
    }
  ]
}